textminer/__init__.py
textminer/cleaner.py
textminer/detector.py
textminer/summarizer.py
textminer_pr0_Bkey-0.1.2.dist-info/LICENSE
textminer_pr0_Bkey-0.1.2.dist-info/METADATA
textminer_pr0_Bkey-0.1.2.dist-info/WHEEL
textminer_pr0_Bkey-0.1.2.dist-info/top_level.txt
textminer_pr0_Bkey-0.1.2.dist-info/RECORD
