Metadata-Version: 2.1
Name: textminer-pr0-Bkey
Version: 0.1.2
Summary: A simple text processing library with stopword removal and keyword extraction. - OSS과제
Author: keily_ae_Embuth
Author-email: 2243104@donga.ac.kr
Classifier: Programming Language :: Python :: 3
Classifier: License :: OSI Approved :: MIT License
Classifier: Operating System :: OS Independent
Requires-Python: >=3.6
License-File: LICENSE
Requires-Dist: nltk
Requires-Dist: scikit-learn
Requires-Dist: numpy
